shade/__init__.py
shade/_adapter.py
shade/_legacy_clients.py
shade/_log.py
shade/_normalize.py
shade/_utils.py
shade/exc.py
shade/inventory.py
shade/meta.py
shade/openstackcloud.py
shade/operatorcloud.py
shade/task_manager.py
shade/_heat/__init__.py
shade/_heat/environment_format.py
shade/_heat/event_utils.py
shade/_heat/template_format.py
shade/_heat/template_utils.py
shade/_heat/utils.py
shade/cmd/__init__.py
shade/cmd/inventory.py
shade/tests/__init__.py
shade/tests/base.py
shade/tests/fakes.py
shade/tests/ansible/README.txt
shade/tests/ansible/run.yml
shade/tests/ansible/hooks/post_test_hook.sh
shade/tests/ansible/roles/auth/tasks/main.yml
shade/tests/ansible/roles/client_config/tasks/main.yml
shade/tests/ansible/roles/group/tasks/main.yml
shade/tests/ansible/roles/group/vars/main.yml
shade/tests/ansible/roles/image/tasks/main.yml
shade/tests/ansible/roles/image/vars/main.yml
shade/tests/ansible/roles/keypair/tasks/main.yml
shade/tests/ansible/roles/keypair/vars/main.yml
shade/tests/ansible/roles/keystone_domain/tasks/main.yml
shade/tests/ansible/roles/keystone_domain/vars/main.yml
shade/tests/ansible/roles/keystone_role/tasks/main.yml
shade/tests/ansible/roles/keystone_role/vars/main.yml
shade/tests/ansible/roles/network/tasks/main.yml
shade/tests/ansible/roles/network/vars/main.yml
shade/tests/ansible/roles/nova_flavor/tasks/main.yml
shade/tests/ansible/roles/object/tasks/main.yml
shade/tests/ansible/roles/port/tasks/main.yml
shade/tests/ansible/roles/port/vars/main.yml
shade/tests/ansible/roles/router/tasks/main.yml
shade/tests/ansible/roles/router/vars/main.yml
shade/tests/ansible/roles/security_group/tasks/main.yml
shade/tests/ansible/roles/security_group/vars/main.yml
shade/tests/ansible/roles/server/tasks/main.yml
shade/tests/ansible/roles/server/vars/main.yaml
shade/tests/ansible/roles/subnet/tasks/main.yml
shade/tests/ansible/roles/subnet/vars/main.yml
shade/tests/ansible/roles/user/tasks/main.yml
shade/tests/ansible/roles/user_group/tasks/main.yml
shade-1.32.0.dist-info/AUTHORS
shade-1.32.0.dist-info/LICENSE
shade-1.32.0.dist-info/METADATA
shade-1.32.0.dist-info/WHEEL
shade-1.32.0.dist-info/entry_points.txt
shade-1.32.0.dist-info/pbr.json
shade-1.32.0.dist-info/top_level.txt
shade-1.32.0.dist-info/RECORD
